{
  "name": "Agro Task Log",
  "short_name": "AgroLog",
  "description": "Agricultural Task & Inventory Management System",
  "start_url": "./",
  "display": "standalone",
  "background_color": "#fafbf6",
  "theme_color": "#2d5016",
  "icons": [
    {
      "src": "data:image/svg+xml,%3Csvg xmlns='http://www.w3.org/2000/svg' viewBox='0 0 192 192'%3E%3Crect width='192' height='192' fill='%232d5016' rx='40'/%3E%3Ctext x='50%25' y='50%25' dominant-baseline='middle' text-anchor='middle' font-size='100' fill='%23fff'%3E🌱%3C/text%3E%3C/svg%3E",
      "sizes": "192x192",
      "type": "image/svg+xml",
      "purpose": "any maskable"
    },
    {
      "src": "data:image/svg+xml,%3Csvg xmlns='http://www.w3.org/2000/svg' viewBox='0 0 512 512'%3E%3Crect width='512' height='512' fill='%232d5016' rx='100'/%3E%3Ctext x='50%25' y='50%25' dominant-baseline='middle' text-anchor='middle' font-size='280' fill='%23fff'%3E🌱%3C/text%3E%3C/svg%3E",
      "sizes": "512x512",
      "type": "image/svg+xml",
      "purpose": "any maskable"
    }
  ]
}